  {
  
  "browsers": [ 
    
    {
      "type":"Mozilla",
      "icon":"mdi-firefox",
      "device_id": 1
    },
    
    {
      "type": "Chrome",
      "icon": "mdi-google-chrome",
      "device_id": 2
    },

    {
      "type": "Safari",
      "icon": "mdi-apple-safari",
      "device_id": 3
    },
    {
      "type":"IE",
      "icon": "mdi-internet-explorer",
      "device_id": 4
    },
    {
      "type": "Opera",
      "icon": "mdi-opera",
      "device_id": 5
    }
  ],

  "operatingsystems": [

    {
      "type":"Windows",
      "icon": "mdi-windows",
      "device_id": 6
    }, 
    {
      "type":"Linux",
      "icon": "mdi-linux",
      "device_id": 5
    },
    {
      "type":"Mac",
      "icon":"mdi-apple",
      "device_id": 4
    },
    {
      "type":"Android",
      "icon":"mdi-android",
      "device_id": 1
    },
    {
      "type":"iOS",
      "icon":"mdi-apple",
      "device_id": 3
    },
    {
      "device_id": 2,
      "type":"Blackberry",
      "icon":"mdi-blackberry"
    }
  ],

  "devices" : [
    {
      "type":"Desktop",
      "icon": "mdi-desktop-mac",
      "device_id": 2
    },

    {
      "type": "Mobile",
      "icon": "mdi-cellphone",
      "device_id": 4
    },
    {
      "type":"Tablet",
      "icon":"mdi-tablet",
      "device_id":5
    }
  ]
}
